PyARMViz/PyARMViz.py
PyARMViz/Rule.py
PyARMViz/__init__.py
PyARMViz/datasets/Online_Retail_Grouped.tar.xz
PyARMViz/datasets/Online_Retail_Rules.json
PyARMViz/datasets/__init__.py
PyARMViz/tests/.~lock.Online Retail.csv#
PyARMViz/tests/unit_tests.py
pyarmviz-0.1.4.dist-info/WHEEL
pyarmviz-0.1.4.dist-info/METADATA
pyarmviz-0.1.4.dist-info/RECORD
