Metadata-Version: 2.1
Name: pyarmviz
Version: 0.1.4
Summary: Advanced Python Association Rule Visualization Library
Home-page: https://github.com/mazeofthemind/PyARMViz
License: MIT
Keywords: packaging,dependency,infer,pyproject.toml
Author: Mazeofthemind
Classifier: License :: OSI Approved :: MIT License
Classifier: Programming Language :: Python :: 2
Classifier: Programming Language :: Python :: 2.7
Classifier: Programming Language :: Python :: 3
Classifier: Programming Language :: Python :: 3.4
Classifier: Programming Language :: Python :: 3.5
Classifier: Programming Language :: Python :: 3.6
Classifier: Programming Language :: Python :: 3.7
Classifier: Programming Language :: Python :: 3.8
Requires-Dist: networkx
Requires-Dist: numpy
Requires-Dist: plotly
Project-URL: Documentation, https://github.com/mazeofthemind/PyARMViz
Project-URL: Repository, https://github.com/mazeofthemind/PyARMViz
